{
  "countries": [
    {
      "region": "Азия",
      "subregion": "Южная Азия",
      "flag": "https://restcountries.eu/data/afg.svg",
      "name": "Афганистан",
      "alpha2Code": "AF",
      "currencies": [
        {
          "code": "AFN",
          "name": "Афганский афгани",
          "symbol": "؋"
        }
      ],
      "englishName": "Afghanistan"
    },
    {
      "region": "Европа",
      "subregion": "Северная Европа",
      "flag": "https://restcountries.eu/data/ala.svg",
      "name": "Аландские острова",
      "alpha2Code": "AX",
      "currencies": [
        {
          "code": "EUR",
          "name": "Евро",
          "symbol": "€"
        }
      ],
      "englishName": "Aland Islands"
    },
    {
      "region": "Европа",
      "subregion": "Южная Европа",
      "flag": "https://restcountries.eu/data/alb.svg",
      "name": "Албания",
      "alpha2Code": "AL",
      "currencies": [
        {
          "code": "ALL",
          "name": "Албанский лек",
          "symbol": "L"
        }
      ],
      "englishName": "Albania"
    },
    {
      "region": "Африка",
      "subregion": "Северная Африка",
      "flag": "https://restcountries.eu/data/dza.svg",
      "name": "Алжир",
      "alpha2Code": "DZ",
      "currencies": [
        {
          "code": "DZD",
          "name": "Алжирский динар",
          "symbol": "د.ج"
        }
      ],
      "englishName": "Algeria"
    },
    {
      "region": "Океания",
      "subregion": "Полинезия",
      "flag": "https://restcountries.eu/data/asm.svg",
      "name": "Американское Самоа",
      "alpha2Code": "AS",
      "currencies": [
        {
          "code": "USD",
          "name": "Доллар США",
          "symbol": "$"
        }
      ],
      "englishName": "American Samoa"
    },
    {
      "region": "Европа",
      "subregion": "Южная Европа",
      "flag": "https://restcountries.eu/data/and.svg",
      "name": "Андорра",
      "alpha2Code": "AD",
      "currencies": [
        {
          "code": "EUR",
          "name": "Евро",
          "symbol": "€"
        }
      ],
      "englishName": "Andorra"
    },
    {
      "region": "Африка",
      "subregion": "Средняя Африка",
      "flag": "https://restcountries.eu/data/ago.svg",
      "name": "Ангола",
      "alpha2Code": "AO",
      "currencies": [
        {
          "code": "AOA",
          "name": "Ангольская кванза",
          "symbol": "Kz"
        }
      ],
      "englishName": "Angola"
    },
    {
      "region": "Америка",
      "subregion": "Карибы",
      "flag": "https://restcountries.eu/data/aia.svg",
      "name": "Ангилья",
      "alpha2Code": "AI",
      "currencies": [
        {
          "code": "XCD",
          "name": "Восточный Карибский доллар",
          "symbol": "$"
        }
      ],
      "englishName": "Anguilla"
    },
    {
      "region": "Америка",
      "subregion": "Карибы",
      "flag": "https://restcountries.eu/data/atg.svg",
      "name": "Антигуа и Барбуда",
      "alpha2Code": "AG",
      "currencies": [
        {
          "code": "XCD",
          "name": "Восточный Карибский доллар",
          "symbol": "$"
        }
      ],
      "englishName": "Antigua and Barbuda"
    },
    {
      "region": "Америка",
      "subregion": "Южная America",
      "flag": "https://restcountries.eu/data/arg.svg",
      "name": "Аргентина",
      "alpha2Code": "AR",
      "currencies": [
        {
          "code": "ARS",
          "name": "Аргентинское песо",
          "symbol": "$"
        }
      ],
      "englishName": "Argentina"
    },
    {
      "region": "Азия",
      "subregion": "Западная Азия",
      "flag": "https://restcountries.eu/data/arm.svg",
      "name": "Армения",
      "alpha2Code": "AM",
      "currencies": [
        {
          "code": "AMD",
          "name": "Армянский драм",
          "symbol": null
        }
      ],
      "englishName": "Armenia"
    },
    {
      "region": "Америка",
      "subregion": "Карибы",
      "flag": "https://restcountries.eu/data/abw.svg",
      "name": "Аруба",
      "alpha2Code": "AW",
      "currencies": [
        {
          "code": "AWG",
          "name": "Арубанский флорин",
          "symbol": "ƒ"
        }
      ],
      "englishName": "Aruba"
    },
    {
      "region": "Океания",
      "subregion": "Австралия и Новая Зеландия",
      "flag": "https://restcountries.eu/data/aus.svg",
      "name": "Австралия",
      "alpha2Code": "AU",
      "currencies": [
        {
          "code": "AUD",
          "name": "Австралийский доллар",
          "symbol": "$"
        }
      ],
      "englishName": "Australia"
    },
    {
      "region": "Европа",
      "subregion": "Западная Европа",
      "flag": "https://restcountries.eu/data/aut.svg",
      "name": "Австрия",
      "alpha2Code": "AT",
      "currencies": [
        {
          "code": "EUR",
          "name": "Евро",
          "symbol": "€"
        }
      ],
      "englishName": "Austria"
    },
    {
      "region": "Азия",
      "subregion": "Западная Азия",
      "flag": "https://restcountries.eu/data/aze.svg",
      "name": "Азербайджан",
      "alpha2Code": "AZ",
      "currencies": [
        {
          "code": "AZN",
          "name": "Азербайджанский манат",
          "symbol": null
        }
      ],
      "englishName": "Azerbaijan"
    },
    {
      "region": "Америка",
      "subregion": "Карибы",
      "flag": "https://restcountries.eu/data/bhs.svg",
      "name": "Багамы",
      "alpha2Code": "BS",
      "currencies": [
        {
          "code": "BSD",
          "name": "Багамский доллар",
          "symbol": "$"
        }
      ],
      "englishName": "Bahamas"
    },
    {
      "region": "Азия",
      "subregion": "Западная Азия",
      "flag": "https://restcountries.eu/data/bhr.svg",
      "name": "Бахрейн",
      "alpha2Code": "BH",
      "currencies": [
        {
          "code": "BHD",
          "name": "Бахрейнский динар",
          "symbol": ".د.ب"
        }
      ],
      "englishName": "Bahrain"
    },
    {
      "region": "Азия",
      "subregion": "Южная Азия",
      "flag": "https://restcountries.eu/data/bgd.svg",
      "name": "Бангладеш",
      "alpha2Code": "BD",
      "currencies": [
        {
          "code": "BDT",
          "name": "Бангладешская така",
          "symbol": "৳"
        }
      ],
      "englishName": "Bangladesh"
    },
    {
      "region": "Америка",
      "subregion": "Карибы",
      "flag": "https://restcountries.eu/data/brb.svg",
      "name": "Барбадос",
      "alpha2Code": "BB",
      "currencies": [
        {
          "code": "BBD",
          "name": "Барбадосский доллар",
          "symbol": "$"
        }
      ],
      "englishName": "Barbados"
    },
    {
      "region": "Европа",
      "subregion": "Восточная Европа",
      "flag": "https://restcountries.eu/data/blr.svg",
      "name": "Беларусь",
      "alpha2Code": "BY",
      "currencies": [
        {
          "code": "BYN",
          "name": "Новый беларусский рубль",
          "symbol": "Br"
        },
        {
          "code": "BYR",
          "name": "Старый беларусский рубль",
          "symbol": "Br"
        }
      ],
      "englishName": "Belarus"
    },
    {
      "region": "Европа",
      "subregion": "Западная Европа",
      "flag": "https://restcountries.eu/data/bel.svg",
      "name": "Бельгия",
      "alpha2Code": "BE",
      "currencies": [
        {
          "code": "EUR",
          "name": "Евро",
          "symbol": "€"
        }
      ],
      "englishName": "Belgium"
    },
    {
      "region": "Америка",
      "subregion": "Central America",
      "flag": "https://restcountries.eu/data/blz.svg",
      "name": "Белиз",
      "alpha2Code": "BZ",
      "currencies": [
        {
          "code": "BZD",
          "name": "Белизский доллар",
          "symbol": "$"
        }
      ],
      "englishName": "Belize"
    },
    {
      "region": "Африка",
      "subregion": "Западная Африка",
      "flag": "https://restcountries.eu/data/ben.svg",
      "name": "Бенин",
      "alpha2Code": "BJ",
      "currencies": [
        {
          "code": "XOF",
          "name": "Западноафриканский франк КФА",
          "symbol": "Fr"
        }
      ],
      "englishName": "Benin"
    },
    {
      "region": "Азия",
      "subregion": "Южная Азия",
      "flag": "https://restcountries.eu/data/btn.svg",
      "name": "Бутан",
      "alpha2Code": "BT",
      "currencies": [
        {
          "code": "INR",
          "name": "Индийская рупия",
          "symbol": "₹"
        }
      ],
      "englishName": "Bhutan"
    },
    {
      "region": "Америка",
      "subregion": "Южная America",
      "flag": "https://restcountries.eu/data/bol.svg",
      "name": "Боливия",
      "alpha2Code": "BO",
      "currencies": [
        {
          "code": "BOB",
          "name": "Боливийский боливиано",
          "symbol": "Bs."
        }
      ],
      "englishName": "Bolivia"
    },
    {
      "region": "Америка",
      "subregion": "Карибы",
      "flag": "https://restcountries.eu/data/bes.svg",
      "name": "Бонэйр",
      "alpha2Code": "BQ",
      "currencies": [
        {
          "code": "USD",
          "name": "Доллар США",
          "symbol": "$"
        }
      ],
      "englishName": "Bonaire"
    },
    {
      "region": "Европа",
      "subregion": "Южная Европа",
      "flag": "https://restcountries.eu/data/bih.svg",
      "name": "Босния и Герцеговина",
      "alpha2Code": "BA",
      "currencies": [
        {
          "code": "BAM",
          "name": "Конвертируемая марка Боснии и Герцеговины",
          "symbol": null
        }
      ],
      "englishName": "Bosnia and Herzegovina"
    },
    {
      "region": "Африка",
      "subregion": "Южная Африка",
      "flag": "https://restcountries.eu/data/bwa.svg",
      "name": "Ботсвана",
      "alpha2Code": "BW",
      "currencies": [
        {
          "code": "BWP",
          "name": "Ботсванская пула",
          "symbol": "P"
        }
      ],
      "englishName": "Botswana"
    },
    {
      "region": "Америка",
      "subregion": "Южная America",
      "flag": "https://restcountries.eu/data/bra.svg",
      "name": "Бразилия",
      "alpha2Code": "BR",
      "currencies": [
        {
          "code": "BRL",
          "name": "Бразильский реал",
          "symbol": "R$"
        }
      ],
      "englishName": "Brazil"
    },
    {
      "region": "Африка",
      "subregion": "Восточная Африка",
      "flag": "https://restcountries.eu/data/iot.svg",
      "name": "Британская территория в Индийском океане",
      "alpha2Code": "IO",
      "currencies": [
        {
          "code": "USD",
          "name": "Доллар США",
          "symbol": "$"
        }
      ],
      "englishName": "British Indian Ocean Territory"
    },
    {
      "region": "Америка",
      "subregion": "Карибы",
      "flag": "https://restcountries.eu/data/vir.svg",
      "name": "Американские Виргинские острова",
      "alpha2Code": "VI",
      "currencies": [
        {
          "code": "USD",
          "name": "Доллар США",
          "symbol": "$"
        }
      ],
      "englishName": "Virgin Islands"
    },
    {
      "region": "Азия",
      "subregion": "Юго-Восточная Азия",
      "flag": "https://restcountries.eu/data/brn.svg",
      "name": "Бруней",
      "alpha2Code": "BN",
      "currencies": [
        {
          "code": "BND",
          "name": "Брунейский доллар",
          "symbol": "$"
        },
        {
          "code": "SGD",
          "name": "Сингапурский доллар",
          "symbol": "$"
        }
      ],
      "englishName": "Brunei Darussalam"
    },
    {
      "region": "Европа",
      "subregion": "Восточная Европа",
      "flag": "https://restcountries.eu/data/bgr.svg",
      "name": "Болгария",
      "alpha2Code": "BG",
      "currencies": [
        {
          "code": "BGN",
          "name": "Болгарский лев",
          "symbol": "лв"
        }
      ],
      "englishName": "Bulgaria"
    },
    {
      "region": "Африка",
      "subregion": "Западная Африка",
      "flag": "https://restcountries.eu/data/bfa.svg",
      "name": "Буркина-Фасо",
      "alpha2Code": "BF",
      "currencies": [
        {
          "code": "XOF",
          "name": "Западноафриканский франк КФА",
          "symbol": "Fr"
        }
      ],
      "englishName": "Burkina Faso"
    },
    {
      "region": "Африка",
      "subregion": "Восточная Африка",
      "flag": "https://restcountries.eu/data/bdi.svg",
      "name": "Бурунди",
      "alpha2Code": "BI",
      "currencies": [
        {
          "code": "BIF",
          "name": "Бурундийский франк",
          "symbol": "Fr"
        }
      ],
      "englishName": "Burundi"
    },
    {
      "region": "Азия",
      "subregion": "Южная-Восточная Азия",
      "flag": "https://restcountries.eu/data/khm.svg",
      "name": "Камбоджа",
      "alpha2Code": "KH",
      "currencies": [
        {
          "code": "KHR",
          "name": "Камбоджийский риель",
          "symbol": "៛"
        },
        {
          "code": "USD",
          "name": "Доллар США",
          "symbol": "$"
        }
      ],
      "englishName": "Cambodia"
    },
    {
      "region": "Африка",
      "subregion": "Средняя Африка",
      "flag": "https://restcountries.eu/data/cmr.svg",
      "name": "Камерун",
      "alpha2Code": "CM",
      "currencies": [
        {
          "code": "XAF",
          "name": "Центральноафриканский франк КФА",
          "symbol": "Fr"
        }
      ],
      "englishName": "Cameroon"
    },
    {
      "region": "Америка",
      "subregion": "Северная America",
      "flag": "https://restcountries.eu/data/can.svg",
      "name": "Канада",
      "alpha2Code": "CA",
      "currencies": [
        {
          "code": "CAD",
          "name": "Канадский доллар",
          "symbol": "$"
        }
      ],
      "englishName": "Canada"
    },
    {
      "region": "Африка",
      "subregion": "Средняя Африка",
      "flag": "https://restcountries.eu/data/caf.svg",
      "name": "Центральная Африканская Республика",
      "alpha2Code": "CF",
      "currencies": [
        {
          "code": "XAF",
          "name": "Центральноафриканский франк КФА",
          "symbol": "Fr"
        }
      ],
      "englishName": "Central African Republic"
    },
    {
      "region": "Африка",
      "subregion": "Средняя Африка",
      "flag": "https://restcountries.eu/data/tcd.svg",
      "name": "Чад",
      "alpha2Code": "TD",
      "currencies": [
        {
          "code": "XAF",
          "name": "Центральноафриканский франк КФА",
          "symbol": "Fr"
        }
      ],
      "englishName": "Chad"
    },
    {
      "region": "Америка",
      "subregion": "Южная Америка",
      "flag": "https://restcountries.eu/data/chl.svg",
      "name": "Чили",
      "alpha2Code": "CL",
      "currencies": [
        {
          "code": "CLP",
          "name": "Чилийское песо",
          "symbol": "$"
        }
      ],
      "englishName": "Chile"
    },
    {
      "region": "Азия",
      "subregion": "Восточная Азия",
      "flag": "https://restcountries.eu/data/chn.svg",
      "name": "Китай",
      "alpha2Code": "CN",
      "currencies": [
        {
          "code": "CNY",
          "name": "Китайский юань",
          "symbol": "¥"
        }
      ],
      "englishName": "China"
    },
    {
      "region": "Океания",
      "subregion": "Australia and New Zealand",
      "flag": "https://restcountries.eu/data/cxr.svg",
      "name": "Остров Рождества",
      "alpha2Code": "CX",
      "currencies": [
        {
          "code": "AUD",
          "name": "Австралийский доллар",
          "symbol": "$"
        }
      ],
      "englishName": "Christmas Island"
    },
    {
      "region": "Океания",
      "subregion": "Australia and New Zealand",
      "flag": "https://restcountries.eu/data/cck.svg",
      "name": "Cocos Islands",
      "alpha2Code": "CC",
      "currencies": [
        {
          "code": "AUD",
          "name": "Австралийский доллар",
          "symbol": "$"
        }
      ],
      "englishName": "Cocos Islands"
    },
    {
      "region": "Америка",
      "subregion": "Южная America",
      "flag": "https://restcountries.eu/data/col.svg",
      "name": "Колумбия",
      "alpha2Code": "CO",
      "currencies": [
        {
          "code": "COP",
          "name": "Колумбийский песо",
          "symbol": "$"
        }
      ],
      "englishName": "Colombia"
    },
    {
      "region": "Африка",
      "subregion": "Восточная Африка",
      "flag": "https://restcountries.eu/data/com.svg",
      "name": "Коморы",
      "alpha2Code": "KM",
      "currencies": [
        {
          "code": "KMF",
          "name": "Франк Комор",
          "symbol": "Fr"
        }
      ],
      "englishName": "Comoros"
    },
    {
      "region": "Африка",
      "subregion": "Средняя Африка",
      "flag": "https://restcountries.eu/data/cod.svg",
      "name": "Конго",
      "alpha2Code": "CD",
      "currencies": [
        {
          "code": "CDF",
          "name": "Конголезский франк",
          "symbol": "Fr"
        }
      ],
      "englishName": "Congo"
    },
    {
      "region": "Океания",
      "subregion": "Полинезия",
      "flag": "https://restcountries.eu/data/cok.svg",
      "name": "Острова Кука",
      "alpha2Code": "CK",
      "currencies": [
        {
          "code": "NZD",
          "name": "Новозеландский доллар",
          "symbol": "$"
        },
        {
          "code": "CKD",
          "name": "Доллар Островов Кука",
          "symbol": "$"
        }
      ],
      "englishName": "Cook Islands"
    },
    {
      "region": "Америка",
      "subregion": "Central America",
      "flag": "https://restcountries.eu/data/cri.svg",
      "name": "Коста-Рика",
      "alpha2Code": "CR",
      "currencies": [
        {
          "code": "CRC",
          "name": "Коста-риканский колон",
          "symbol": "₡"
        }
      ],
      "englishName": "Costa Rica"
    },
    {
      "region": "Европа",
      "subregion": "Южная Европа",
      "flag": "https://restcountries.eu/data/hrv.svg",
      "name": "Хорватия",
      "alpha2Code": "HR",
      "currencies": [
        {
          "code": "HRK",
          "name": "Хорватская куна",
          "symbol": "kn"
        }
      ],
      "englishName": "Croatia"
    },
    {
      "region": "Америка",
      "subregion": "Карибы",
      "flag": "https://restcountries.eu/data/cub.svg",
      "name": "Куба",
      "alpha2Code": "CU",
      "currencies": [
        {
          "code": "CUP",
          "name": "Кубинское песо",
          "symbol": "$"
        }
      ],
      "englishName": "Cuba"
    },
    {
      "region": "Америка",
      "subregion": "Карибы",
      "flag": "https://restcountries.eu/data/cuw.svg",
      "name": "Кюрасао",
      "alpha2Code": "CW",
      "currencies": [
        {
          "code": "ANG",
          "name": "Нидерландский антильский гульден",
          "symbol": "ƒ"
        }
      ],
      "englishName": "Curacao"
    },
    {
      "region": "Европа",
      "subregion": "Южная Европа",
      "flag": "https://restcountries.eu/data/cyp.svg",
      "name": "Кипр",
      "alpha2Code": "CY",
      "currencies": [
        {
          "code": "EUR",
          "name": "Евро",
          "symbol": "€"
        }
      ],
      "englishName": "Cyprus"
    },
    {
      "region": "Европа",
      "subregion": "Восточная Европа",
      "flag": "https://restcountries.eu/data/cze.svg",
      "name": "Чешская республика",
      "alpha2Code": "CZ",
      "currencies": [
        {
          "code": "CZK",
          "name": "Чешская крона",
          "symbol": "Kč"
        }
      ],
      "englishName": "Czech Republic"
    },
    {
      "region": "Европа",
      "subregion": "Северная Европа",
      "flag": "https://restcountries.eu/data/dnk.svg",
      "name": "Дания",
      "alpha2Code": "DK",
      "currencies": [
        {
          "code": "DKK",
          "name": "Датская крона",
          "symbol": "kr"
        }
      ],
      "englishName": "Denmark"
    },
    {
      "region": "Африка",
      "subregion": "Восточная Африка",
      "flag": "https://restcountries.eu/data/dji.svg",
      "name": "Джибути",
      "alpha2Code": "DJ",
      "currencies": [
        {
          "code": "DJF",
          "name": "Франк Джибути",
          "symbol": "Fr"
        }
      ],
      "englishName": "Djibouti"
    },
    {
      "region": "Америка",
      "subregion": "Карибы",
      "flag": "https://restcountries.eu/data/dma.svg",
      "name": "Доминика",
      "alpha2Code": "DM",
      "currencies": [
        {
          "code": "XCD",
          "name": "Восточнокарибский доллар",
          "symbol": "$"
        }
      ],
      "englishName": "Dominica"
    },
    {
      "region": "Америка",
      "subregion": "Карибы",
      "flag": "https://restcountries.eu/data/dom.svg",
      "name": "Доминиканская Республика",
      "alpha2Code": "DO",
      "currencies": [
        {
          "code": "DOP",
          "name": "Доминиканское песо",
          "symbol": "$"
        }
      ],
      "englishName": "Dominican Republic"
    },
    {
      "region": "Америка",
      "subregion": "Южная America",
      "flag": "https://restcountries.eu/data/ecu.svg",
      "name": "Эквадор",
      "alpha2Code": "EC",
      "currencies": [
        {
          "code": "USD",
          "name": "Доллар США",
          "symbol": "$"
        }
      ],
      "englishName": "Ecuador"
    },
    {
      "region": "Африка",
      "subregion": "Северная Африка",
      "flag": "https://restcountries.eu/data/egy.svg",
      "name": "Египет",
      "alpha2Code": "EG",
      "currencies": [
        {
          "code": "EGP",
          "name": "Египетский фунт",
          "symbol": "£"
        }
      ],
      "englishName": "Egypt"
    },
    {
      "region": "Америка",
      "subregion": "Central America",
      "flag": "https://restcountries.eu/data/slv.svg",
      "name": "Сальвадор",
      "alpha2Code": "SV",
      "currencies": [
        {
          "code": "USD",
          "name": "Доллар США",
          "symbol": "$"
        }
      ],
      "englishName": "El Salvador"
    },
    {
      "region": "Африка",
      "subregion": "Средняя Африка",
      "flag": "https://restcountries.eu/data/gnq.svg",
      "name": "Экваториальная Гвинея",
      "alpha2Code": "GQ",
      "currencies": [
        {
          "code": "XAF",
          "name": "Центральноафриканский франк КФА",
          "symbol": "Fr"
        }
      ],
      "englishName": "Equatorial Guinea"
    },
    {
      "region": "Африка",
      "subregion": "Восточная Африка",
      "flag": "https://restcountries.eu/data/eri.svg",
      "name": "Эритрея",
      "alpha2Code": "ER",
      "currencies": [
        {
          "code": "ERN",
          "name": "Эритрейская накфа",
          "symbol": "Nfk"
        }
      ],
      "englishName": "Eritrea"
    },
    {
      "region": "Европа",
      "subregion": "Северная Европа",
      "flag": "https://restcountries.eu/data/est.svg",
      "name": "Эстония",
      "alpha2Code": "EE",
      "currencies": [
        {
          "code": "EUR",
          "name": "Евро",
          "symbol": "€"
        }
      ],
      "englishName": "Estonia"
    },
    {
      "region": "Африка",
      "subregion": "Восточная Африка",
      "flag": "https://restcountries.eu/data/eth.svg",
      "name": "Эфиопия",
      "alpha2Code": "ET",
      "currencies": [
        {
          "code": "ETB",
          "name": "Эфиопский быр",
          "symbol": "Br"
        }
      ],
      "englishName": "Ethiopia"
    },
    {
      "region": "Европа",
      "subregion": "Северная Европа",
      "flag": "https://restcountries.eu/data/fro.svg",
      "name": "Фарерский острова",
      "alpha2Code": "FO",
      "currencies": [
        {
          "code": "DKK",
          "name": "Датская крона",
          "symbol": "kr"
        }
      ],
      "englishName": "Faroe Islands"
    },
    {
      "region": "Океания",
      "subregion": "Melanesia",
      "flag": "https://restcountries.eu/data/fji.svg",
      "name": "Фиджи",
      "alpha2Code": "FJ",
      "currencies": [
        {
          "code": "FJD",
          "name": "Доллар Фиджи",
          "symbol": "$"
        }
      ],
      "englishName": "Fiji"
    },
    {
      "region": "Европа",
      "subregion": "Северная Европа",
      "flag": "https://restcountries.eu/data/fin.svg",
      "name": "Финляндия",
      "alpha2Code": "FI",
      "currencies": [
        {
          "code": "EUR",
          "name": "Евро",
          "symbol": "€"
        }
      ],
      "englishName": "Finland"
    },
    {
      "region": "Европа",
      "subregion": "Западная Европа",
      "flag": "https://restcountries.eu/data/fra.svg",
      "name": "Франция",
      "alpha2Code": "FR",
      "currencies": [
        {
          "code": "EUR",
          "name": "Евро",
          "symbol": "€"
        }
      ],
      "englishName": "France"
    },
    {
      "region": "Океания",
      "subregion": "Полинезия",
      "flag": "https://restcountries.eu/data/pyf.svg",
      "name": "Французская Полинезия",
      "alpha2Code": "PF",
      "currencies": [
        {
          "code": "XPF",
          "name": "Тихоокеанский франк",
          "symbol": "Fr"
        }
      ],
      "englishName": "French Полинезия"
    },
    {
      "region": "Африка",
      "subregion": "Средняя Африка",
      "flag": "https://restcountries.eu/data/gab.svg",
      "name": "Габон",
      "alpha2Code": "GA",
      "currencies": [
        {
          "code": "XAF",
          "name": "Центральноафриканский франк КФА",
          "symbol": "Fr"
        }
      ],
      "englishName": "Gabon"
    },
    {
      "region": "Африка",
      "subregion": "Западная Африка",
      "flag": "https://restcountries.eu/data/gmb.svg",
      "name": "Гамбия",
      "alpha2Code": "GM",
      "currencies": [
        {
          "code": "GMD",
          "name": "Гамбийский даласи",
          "symbol": "D"
        }
      ],
      "englishName": "Gambia"
    },
    {
      "region": "Азия",
      "subregion": "Западная Азия",
      "flag": "https://restcountries.eu/data/geo.svg",
      "name": "Грузия",
      "alpha2Code": "GE",
      "currencies": [
        {
          "code": "GEL",
          "name": "Грузинский лари",
          "symbol": "ლ"
        }
      ],
      "englishName": "Georgia"
    },
    {
      "region": "Европа",
      "subregion": "Западная Европа",
      "flag": "https://restcountries.eu/data/deu.svg",
      "name": "Германия",
      "alpha2Code": "DE",
      "currencies": [
        {
          "code": "EUR",
          "name": "Евро",
          "symbol": "€"
        }
      ],
      "englishName": "Germany"
    },
    {
      "region": "Африка",
      "subregion": "Западная Африка",
      "flag": "https://restcountries.eu/data/gha.svg",
      "name": "Гана",
      "alpha2Code": "GH",
      "currencies": [
        {
          "code": "GHS",
          "name": "Ганский седи",
          "symbol": "₵"
        }
      ],
      "englishName": "Ghana"
    },
    {
      "region": "Европа",
      "subregion": "Южная Европа",
      "flag": "https://restcountries.eu/data/gib.svg",
      "name": "Гибралтар",
      "alpha2Code": "GI",
      "currencies": [
        {
          "code": "GIP",
          "name": "Гибралтарский фунт",
          "symbol": "£"
        }
      ],
      "englishName": "Gibraltar"
    },
    {
      "region": "Европа",
      "subregion": "Южная Европа",
      "flag": "https://restcountries.eu/data/grc.svg",
      "name": "Греция",
      "alpha2Code": "GR",
      "currencies": [
        {
          "code": "EUR",
          "name": "Евро",
          "symbol": "€"
        }
      ],
      "englishName": "Greece"
    },
    {
      "region": "Америка",
      "subregion": "Северная America",
      "flag": "https://restcountries.eu/data/grl.svg",
      "name": "Гренландия",
      "alpha2Code": "GL",
      "currencies": [
        {
          "code": "DKK",
          "name": "Датская крона",
          "symbol": "kr"
        }
      ],
      "englishName": "Greenland"
    },
    {
      "region": "Америка",
      "subregion": "Карибы",
      "flag": "https://restcountries.eu/data/grd.svg",
      "name": "Гренада",
      "alpha2Code": "GD",
      "currencies": [
        {
          "code": "XCD",
          "name": "Восточнокарибский доллар",
          "symbol": "$"
        }
      ],
      "englishName": "Grenada"
    },
    {
      "region": "Океания",
      "subregion": "Micronesia",
      "flag": "https://restcountries.eu/data/gum.svg",
      "name": "Гуам",
      "alpha2Code": "GU",
      "currencies": [
        {
          "code": "USD",
          "name": "Доллар США",
          "symbol": "$"
        }
      ],
      "englishName": "Guam"
    },
    {
      "region": "Америка",
      "subregion": "Central America",
      "flag": "https://restcountries.eu/data/gtm.svg",
      "name": "Гватемала",
      "alpha2Code": "GT",
      "currencies": [
        {
          "code": "GTQ",
          "name": "Гватемальский кетсаль",
          "symbol": "Q"
        }
      ],
      "englishName": "Guatemala"
    },
    {
      "region": "Европа",
      "subregion": "Северная Европа",
      "flag": "https://restcountries.eu/data/ggy.svg",
      "name": "Гернси",
      "alpha2Code": "GG",
      "currencies": [
        {
          "code": "GBP",
          "name": "Фунт стерлингов",
          "symbol": "£"
        }
      ],
      "englishName": "Guernsey"
    },
    {
      "region": "Африка",
      "subregion": "Западная Африка",
      "flag": "https://restcountries.eu/data/gin.svg",
      "name": "Гвинея",
      "alpha2Code": "GN",
      "currencies": [
        {
          "code": "GNF",
          "name": "Гвинейский франк",
          "symbol": "Fr"
        }
      ],
      "englishName": "Guinea"
    },
    {
      "region": "Африка",
      "subregion": "Западная Африка",
      "flag": "https://restcountries.eu/data/gnb.svg",
      "name": "Гвинея-Бисау",
      "alpha2Code": "GW",
      "currencies": [
        {
          "code": "XOF",
          "name": "Западноафриканский франк КФА",
          "symbol": "Fr"
        }
      ],
      "englishName": "Guinea Bissau"
    },
    {
      "region": "Америка",
      "subregion": "Южная America",
      "flag": "https://restcountries.eu/data/guy.svg",
      "name": "Гайана",
      "alpha2Code": "GY",
      "currencies": [
        {
          "code": "GYD",
          "name": "Гайанский доллар",
          "symbol": "$"
        }
      ],
      "englishName": "Guyana"
    },
    {
      "region": "Америка",
      "subregion": "Карибы",
      "flag": "https://restcountries.eu/data/hti.svg",
      "name": "Гаити",
      "alpha2Code": "HT",
      "currencies": [
        {
          "code": "HTG",
          "name": "Гаитянский гурд",
          "symbol": "G"
        }
      ],
      "englishName": "Haiti"
    },
    {
      "region": "Америка",
      "subregion": "Central America",
      "flag": "https://restcountries.eu/data/hnd.svg",
      "name": "Гондурас",
      "alpha2Code": "HN",
      "currencies": [
        {
          "code": "HNL",
          "name": "Гондурасская лемпира",
          "symbol": "L"
        }
      ],
      "englishName": "Honduras"
    },
    {
      "region": "Азия",
      "subregion": "Восточная Азия",
      "flag": "https://restcountries.eu/data/hkg.svg",
      "name": "Гонконг",
      "alpha2Code": "HK",
      "currencies": [
        {
          "code": "HKD",
          "name": "Гонконгский доллар",
          "symbol": "$"
        }
      ],
      "englishName": "Hong Kong"
    },
    {
      "region": "Европа",
      "subregion": "Восточная Европа",
      "flag": "https://restcountries.eu/data/hun.svg",
      "name": "Венгрия",
      "alpha2Code": "HU",
      "currencies": [
        {
          "code": "HUF",
          "name": "Венгерский форинт",
          "symbol": "Ft"
        }
      ],
      "englishName": "Hungary"
    },
    {
      "region": "Европа",
      "subregion": "Северная Европа",
      "flag": "https://restcountries.eu/data/isl.svg",
      "name": "Исландия",
      "alpha2Code": "IS",
      "currencies": [
        {
          "code": "ISK",
          "name": "Исландская крона",
          "symbol": "kr"
        }
      ],
      "englishName": "Iceland"
    },
    {
      "region": "Азия",
      "subregion": "Южная Азия",
      "flag": "https://restcountries.eu/data/ind.svg",
      "name": "Индия",
      "alpha2Code": "IN",
      "currencies": [
        {
          "code": "INR",
          "name": "Индийская рупия",
          "symbol": "₹"
        }
      ],
      "englishName": "India"
    },
    {
      "region": "Азия",
      "subregion": "Южная-Восточная Азия",
      "flag": "https://restcountries.eu/data/idn.svg",
      "name": "Индонезия",
      "alpha2Code": "ID",
      "currencies": [
        {
          "code": "IDR",
          "name": "Индонезийская рупия",
          "symbol": "Rp"
        }
      ],
      "englishName": "Indonesia"
    },
    {
      "region": "Азия",
      "subregion": "Южная Азия",
      "flag": "https://restcountries.eu/data/irn.svg",
      "name": "Iran",
      "alpha2Code": "IR",
      "currencies": [
        {
          "code": "IRR",
          "name": "Иранский риал",
          "symbol": "﷼"
        }
      ],
      "englishName": "Iran"
    },
    {
      "region": "Азия",
      "subregion": "Западная Азия",
      "flag": "https://restcountries.eu/data/irq.svg",
      "name": "Ирак",
      "alpha2Code": "IQ",
      "currencies": [
        {
          "code": "IQD",
          "name": "Иракский динар",
          "symbol": "ع.د"
        }
      ],
      "englishName": "Iraq"
    },
    {
      "region": "Европа",
      "subregion": "Северная Европа",
      "flag": "https://restcountries.eu/data/irl.svg",
      "name": "Ирландия",
      "alpha2Code": "IE",
      "currencies": [
        {
          "code": "EUR",
          "name": "Евро",
          "symbol": "€"
        }
      ],
      "englishName": "Ireland"
    },
    {
      "region": "Европа",
      "subregion": "Северная Европа",
      "flag": "https://restcountries.eu/data/imn.svg",
      "name": "Остров Мэн",
      "alpha2Code": "IM",
      "currencies": [
        {
          "code": "GBP",
          "name": "Фунт стерлингов",
          "symbol": "£"
        }
      ],
      "englishName": "Isle of Man"
    },
    {
      "region": "Азия",
      "subregion": "Западная Азия",
      "flag": "https://restcountries.eu/data/isr.svg",
      "name": "Израиль",
      "alpha2Code": "IL",
      "currencies": [
        {
          "code": "ILS",
          "name": "Новый израильский шекель",
          "symbol": "₪"
        }
      ],
      "englishName": "Israel"
    },
    {
      "region": "Европа",
      "subregion": "Южная Европа",
      "flag": "https://restcountries.eu/data/ita.svg",
      "name": "Италия",
      "alpha2Code": "IT",
      "currencies": [
        {
          "code": "EUR",
          "name": "Евро",
          "symbol": "€"
        }
      ],
      "englishName": "Italy"
    },
    {
      "region": "Америка",
      "subregion": "Карибы",
      "flag": "https://restcountries.eu/data/jam.svg",
      "name": "Ямайка",
      "alpha2Code": "JM",
      "currencies": [
        {
          "code": "JMD",
          "name": "Ямайский доллар",
          "symbol": "$"
        }
      ],
      "englishName": "Jamaica"
    },
    {
      "region": "Азия",
      "subregion": "Восточная Азия",
      "flag": "https://restcountries.eu/data/jpn.svg",
      "name": "Япония",
      "alpha2Code": "JP",
      "currencies": [
        {
          "code": "JPY",
          "name": "Японская йена",
          "symbol": "¥"
        }
      ],
      "englishName": "Japan"
    },
    {
      "region": "Европа",
      "subregion": "Северная Европа",
      "flag": "https://restcountries.eu/data/jey.svg",
      "name": "Джерси",
      "alpha2Code": "JE",
      "currencies": [
        {
          "code": "GBP",
          "name": "Фунт стерлингов",
          "symbol": "£"
        }
      ],
      "englishName": "Jersey"
    },
    {
      "region": "Азия",
      "subregion": "Западная Азия",
      "flag": "https://restcountries.eu/data/jor.svg",
      "name": "Иордания",
      "alpha2Code": "JO",
      "currencies": [
        {
          "code": "JOD",
          "name": "Иорданский динар",
          "symbol": "د.ا"
        }
      ],
      "englishName": "Jordan"
    },
    {
      "region": "Азия",
      "subregion": "Central Азия",
      "flag": "https://restcountries.eu/data/kaz.svg",
      "name": "Казахстан",
      "alpha2Code": "KZ",
      "currencies": [
        {
          "code": "KZT",
          "name": "Казахстанский тенге",
          "symbol": null
        }
      ],
      "englishName": "Kazakhstan"
    },
    {
      "region": "Африка",
      "subregion": "Восточная Африка",
      "flag": "https://restcountries.eu/data/ken.svg",
      "name": "Кения",
      "alpha2Code": "KE",
      "currencies": [
        {
          "code": "KES",
          "name": "Кенийский шиллинг",
          "symbol": "Sh"
        }
      ],
      "englishName": "Kenya"
    },
    {
      "region": "Океания",
      "subregion": "Micronesia",
      "flag": "https://restcountries.eu/data/kir.svg",
      "name": "Кирибати",
      "alpha2Code": "KI",
      "currencies": [
        {
          "code": "AUD",
          "name": "Австралийский доллар",
          "symbol": "$"
        }
      ],
      "englishName": "Kiribati"
    },
    {
      "region": "Азия",
      "subregion": "Западная Азия",
      "flag": "https://restcountries.eu/data/kwt.svg",
      "name": "Кувейт",
      "alpha2Code": "KW",
      "currencies": [
        {
          "code": "KWD",
          "name": "Кувейтский динар",
          "symbol": "د.ك"
        }
      ],
      "englishName": "Kuwait"
    },
    {
      "region": "Азия",
      "subregion": "Central Азия",
      "flag": "https://restcountries.eu/data/kgz.svg",
      "name": "Киргизия",
      "alpha2Code": "KG",
      "currencies": [
        {
          "code": "KGS",
          "name": "Киргизский сом",
          "symbol": "с"
        }
      ],
      "englishName": "Kyrgyzstan"
    },
    {
      "region": "Азия",
      "subregion": "Южная-Восточная Азия",
      "flag": "https://restcountries.eu/data/lao.svg",
      "name": "Лаос",
      "alpha2Code": "LA",
      "currencies": [
        {
          "code": "LAK",
          "name": "Лаосский кип",
          "symbol": "₭"
        }
      ],
      "englishName": "Laos"
    },
    {
      "region": "Европа",
      "subregion": "Северная Европа",
      "flag": "https://restcountries.eu/data/lva.svg",
      "name": "Латвия",
      "alpha2Code": "LV",
      "currencies": [
        {
          "code": "EUR",
          "name": "Евро",
          "symbol": "€"
        }
      ],
      "englishName": "Latvia"
    },
    {
      "region": "Азия",
      "subregion": "Западная Азия",
      "flag": "https://restcountries.eu/data/lbn.svg",
      "name": "Ливан",
      "alpha2Code": "LB",
      "currencies": [
        {
          "code": "LBP",
          "name": "Ливанский фунт",
          "symbol": "ل.ل"
        }
      ],
      "englishName": "Lebanon"
    },
    {
      "region": "Африка",
      "subregion": "Южная Африка",
      "flag": "https://restcountries.eu/data/lso.svg",
      "name": "Лесото",
      "alpha2Code": "LS",
      "currencies": [
        {
          "code": "LSL",
          "name": "Лоти Лесото",
          "symbol": "L"
        }
      ],
      "englishName": "Lesotho"
    },
    {
      "region": "Африка",
      "subregion": "Западная Африка",
      "flag": "https://restcountries.eu/data/lbr.svg",
      "name": "Либерия",
      "alpha2Code": "LR",
      "currencies": [
        {
          "code": "LRD",
          "name": "Либерийский доллар",
          "symbol": "$"
        }
      ],
      "englishName": "Liberia"
    },
    {
      "region": "Африка",
      "subregion": "Северная Африка",
      "flag": "https://restcountries.eu/data/lby.svg",
      "name": "Ливия",
      "alpha2Code": "LY",
      "currencies": [
        {
          "code": "LYD",
          "name": "Ливийский динар",
          "symbol": "ل.د"
        }
      ],
      "englishName": "Libya"
    },
    {
      "region": "Европа",
      "subregion": "Западная Европа",
      "flag": "https://restcountries.eu/data/lie.svg",
      "name": "Лихтенштейн",
      "alpha2Code": "LI",
      "currencies": [
        {
          "code": "CHF",
          "name": "Швейцарский франк",
          "symbol": "Fr"
        }
      ],
      "englishName": "Liechtenstein"
    },
    {
      "region": "Европа",
      "subregion": "Северная Европа",
      "flag": "https://restcountries.eu/data/ltu.svg",
      "name": "Литва",
      "alpha2Code": "LT",
      "currencies": [
        {
          "code": "EUR",
          "name": "Евро",
          "symbol": "€"
        }
      ],
      "englishName": "Lithuania"
    },
    {
      "region": "Европа",
      "subregion": "Западная Европа",
      "flag": "https://restcountries.eu/data/lux.svg",
      "name": "Люксембург",
      "alpha2Code": "LU",
      "currencies": [
        {
          "code": "EUR",
          "name": "Евро",
          "symbol": "€"
        }
      ],
      "englishName": "Luxembourg"
    },
    {
      "region": "Азия",
      "subregion": "Восточная Азия",
      "flag": "https://restcountries.eu/data/mac.svg",
      "name": "Макао",
      "alpha2Code": "MO",
      "currencies": [
        {
          "code": "MOP",
          "name": "Патака Макао",
          "symbol": "P"
        }
      ],
      "englishName": "Macao"
    },
    {
      "region": "Африка",
      "subregion": "Восточная Африка",
      "flag": "https://restcountries.eu/data/mdg.svg",
      "name": "Мадагаскар",
      "alpha2Code": "MG",
      "currencies": [
        {
          "code": "MGA",
          "name": "Малагасийский ариари",
          "symbol": "Ar"
        }
      ],
      "englishName": "Madagascar"
    },
    {
      "region": "Африка",
      "subregion": "Восточная Африка",
      "flag": "https://restcountries.eu/data/mwi.svg",
      "name": "Малави",
      "alpha2Code": "MW",
      "currencies": [
        {
          "code": "MWK",
          "name": "Малавийская квача",
          "symbol": "MK"
        }
      ],
      "englishName": "Malawi"
    },
    {
      "region": "Азия",
      "subregion": "Южная-Восточная Азия",
      "flag": "https://restcountries.eu/data/mys.svg",
      "name": "Малайзия",
      "alpha2Code": "MY",
      "currencies": [
        {
          "code": "MYR",
          "name": "Малайзийский ринггит",
          "symbol": "RM"
        }
      ],
      "englishName": "Malaysia"
    },
    {
      "region": "Азия",
      "subregion": "Южная Азия",
      "flag": "https://restcountries.eu/data/mdv.svg",
      "name": "Мальдивы",
      "alpha2Code": "MV",
      "currencies": [
        {
          "code": "MVR",
          "name": "Мальдивская руфия",
          "symbol": ".ރ"
        }
      ],
      "englishName": "Maldives"
    },
    {
      "region": "Африка",
      "subregion": "Западная Африка",
      "flag": "https://restcountries.eu/data/mli.svg",
      "name": "Мали",
      "alpha2Code": "ML",
      "currencies": [
        {
          "code": "XOF",
          "name": "Западноафриканский франк КФА",
          "symbol": "Fr"
        }
      ],
      "englishName": "Mali"
    },
    {
      "region": "Европа",
      "subregion": "Южная Европа",
      "flag": "https://restcountries.eu/data/mlt.svg",
      "name": "Мальта",
      "alpha2Code": "MT",
      "currencies": [
        {
          "code": "EUR",
          "name": "Евро",
          "symbol": "€"
        }
      ],
      "englishName": "Malta"
    },
    {
      "region": "Океания",
      "subregion": "Micronesia",
      "flag": "https://restcountries.eu/data/mhl.svg",
      "name": "Маршалловы острова",
      "alpha2Code": "MH",
      "currencies": [
        {
          "code": "USD",
          "name": "Доллар США",
          "symbol": "$"
        }
      ],
      "englishName": "Marshall Islands"
    },
    {
      "region": "Америка",
      "subregion": "Карибы",
      "flag": "https://restcountries.eu/data/mtq.svg",
      "name": "Мартиника",
      "alpha2Code": "MQ",
      "currencies": [
        {
          "code": "EUR",
          "name": "Евро",
          "symbol": "€"
        }
      ],
      "englishName": "Martinique"
    },
    {
      "region": "Африка",
      "subregion": "Восточная Африка",
      "flag": "https://restcountries.eu/data/mus.svg",
      "name": "Остров Маврикий",
      "alpha2Code": "MU",
      "currencies": [
        {
          "code": "MUR",
          "name": "Маврикийская рупия",
          "symbol": "₨"
        }
      ],
      "englishName": "Mauritius"
    },
    {
      "region": "Америка",
      "subregion": "Central America",
      "flag": "https://restcountries.eu/data/mex.svg",
      "name": "Мексика",
      "alpha2Code": "MX",
      "currencies": [
        {
          "code": "MXN",
          "name": "Мексиканское песо",
          "symbol": "$"
        }
      ],
      "englishName": "Mexico"
    },
    {
      "region": "Океания",
      "subregion": "Федеративные Штаты Микронезии",
      "flag": "https://restcountries.eu/data/fsm.svg",
      "name": "Федеративные Штаты Микронезии",
      "alpha2Code": "FM",
      "currencies": [
        {
          "code": "USD",
          "name": "Доллар США",
          "symbol": "$"
        }
      ],
      "englishName": "Micronesia"
    },
    {
      "region": "Европа",
      "subregion": "Восточная Европа",
      "flag": "https://restcountries.eu/data/mda.svg",
      "name": "Молдавия",
      "alpha2Code": "MD",
      "currencies": [
        {
          "code": "MDL",
          "name": "Молдавский лей",
          "symbol": "L"
        }
      ],
      "englishName": "Moldova"
    },
    {
      "region": "Европа",
      "subregion": "Западная Европа",
      "flag": "https://restcountries.eu/data/mco.svg",
      "name": "Монако",
      "alpha2Code": "MC",
      "currencies": [
        {
          "code": "EUR",
          "name": "Евро",
          "symbol": "€"
        }
      ],
      "englishName": "Monaco"
    },
    {
      "region": "Азия",
      "subregion": "Восточная Азия",
      "flag": "https://restcountries.eu/data/mng.svg",
      "name": "Монголия",
      "alpha2Code": "MN",
      "currencies": [
        {
          "code": "MNT",
          "name": "Монгольский тугрик",
          "symbol": "₮"
        }
      ],
      "englishName": "Mongolia"
    },
    {
      "region": "Европа",
      "subregion": "Южная Европа",
      "flag": "https://restcountries.eu/data/mne.svg",
      "name": "Черногория",
      "alpha2Code": "ME",
      "currencies": [
        {
          "code": "EUR",
          "name": "Евро",
          "symbol": "€"
        }
      ],
      "englishName": "Montenegro"
    },
    {
      "region": "Америка",
      "subregion": "Карибы",
      "flag": "https://restcountries.eu/data/msr.svg",
      "name": "Монтсеррат",
      "alpha2Code": "MS",
      "currencies": [
        {
          "code": "XCD",
          "name": "Восточнокарибский доллар",
          "symbol": "$"
        }
      ],
      "englishName": "Montserrat"
    },
    {
      "region": "Африка",
      "subregion": "Северная Африка",
      "flag": "https://restcountries.eu/data/mar.svg",
      "name": "Марокко",
      "alpha2Code": "MA",
      "currencies": [
        {
          "code": "MAD",
          "name": "Марокканский дирхам",
          "symbol": "د.م."
        }
      ],
      "englishName": "Morocco"
    },
    {
      "region": "Африка",
      "subregion": "Восточная Африка",
      "flag": "https://restcountries.eu/data/moz.svg",
      "name": "Мозамбик",
      "alpha2Code": "MZ",
      "currencies": [
        {
          "code": "MZN",
          "name": "Мозамбикский метикал",
          "symbol": "MT"
        }
      ],
      "englishName": "Mozambique"
    },
    {
      "region": "Азия",
      "subregion": "Южная-Восточная Азия",
      "flag": "https://restcountries.eu/data/mmr.svg",
      "name": "Мьянма",
      "alpha2Code": "MM",
      "currencies": [
        {
          "code": "MMK",
          "name": "Мьянманский кьят",
          "symbol": "Ks"
        }
      ],
      "englishName": "Myanmar"
    },
    {
      "region": "Африка",
      "subregion": "Южная Африка",
      "flag": "https://restcountries.eu/data/nam.svg",
      "name": "Намибия",
      "alpha2Code": "NA",
      "currencies": [
        {
          "code": "NAD",
          "name": "Доллар Намибии",
          "symbol": "$"
        },
        {
          "code": "ZAR",
          "name": "Южноафриканский рэнд",
          "symbol": "R"
        }
      ],
      "englishName": "Namibia"
    },
    {
      "region": "Океания",
      "subregion": "Micronesia",
      "flag": "https://restcountries.eu/data/nru.svg",
      "name": "Науру",
      "alpha2Code": "NR",
      "currencies": [
        {
          "code": "AUD",
          "name": "Австралийский доллар",
          "symbol": "$"
        }
      ],
      "englishName": "Nauru"
    },
    {
      "region": "Азия",
      "subregion": "Южная Азия",
      "flag": "https://restcountries.eu/data/npl.svg",
      "name": "Непал",
      "alpha2Code": "NP",
      "currencies": [
        {
          "code": "NPR",
          "name": "Непальская рупия",
          "symbol": "₨"
        }
      ],
      "englishName": "Nepal"
    },
    {
      "region": "Европа",
      "subregion": "Западная Европа",
      "flag": "https://restcountries.eu/data/nld.svg",
      "name": "Нидерланды",
      "alpha2Code": "NL",
      "currencies": [
        {
          "code": "EUR",
          "name": "Евро",
          "symbol": "€"
        }
      ],
      "englishName": "Netherlands"
    },
    {
      "region": "Океания",
      "subregion": "Australia and New Zealand",
      "flag": "https://restcountries.eu/data/nzl.svg",
      "name": "Новая Зеландия",
      "alpha2Code": "NZ",
      "currencies": [
        {
          "code": "NZD",
          "name": "Новозеландский доллар",
          "symbol": "$"
        }
      ],
      "englishName": "New Zealand"
    },
    {
      "region": "Америка",
      "subregion": "Central America",
      "flag": "https://restcountries.eu/data/nic.svg",
      "name": "Никарагуа",
      "alpha2Code": "NI",
      "currencies": [
        {
          "code": "NIO",
          "name": "Никарагуанская кордоба",
          "symbol": "C$"
        }
      ],
      "englishName": "Nicaragua"
    },
    {
      "region": "Африка",
      "subregion": "Западная Африка",
      "flag": "https://restcountries.eu/data/ner.svg",
      "name": "Нигер",
      "alpha2Code": "NE",
      "currencies": [
        {
          "code": "XOF",
          "name": "Западноафриканский франк КФА",
          "symbol": "Fr"
        }
      ],
      "englishName": "Niger"
    },
    {
      "region": "Африка",
      "subregion": "Западная Африка",
      "flag": "https://restcountries.eu/data/nga.svg",
      "name": "Нигерия",
      "alpha2Code": "NG",
      "currencies": [
        {
          "code": "NGN",
          "name": "Нигерийская найра",
          "symbol": "₦"
        }
      ],
      "englishName": "Nigeria"
    },
    {
      "region": "Океания",
      "subregion": "Полинезия",
      "flag": "https://restcountries.eu/data/niu.svg",
      "name": "Niue",
      "alpha2Code": "NU",
      "currencies": [
        {
          "code": "NZD",
          "name": "New Zealand dollar",
          "symbol": "$"
        }
      ],
      "englishName": "Niue"
    },
    {
      "region": "Океания",
      "subregion": "Australia and New Zealand",
      "flag": "https://restcountries.eu/data/nfk.svg",
      "name": "Norfolk Island",
      "alpha2Code": "NF",
      "currencies": [
        {
          "code": "AUD",
          "name": "Австралийский доллар",
          "symbol": "$"
        }
      ],
      "englishName": "Norfolk Island"
    },
    {
      "region": "Океания",
      "subregion": "Micronesia",
      "flag": "https://restcountries.eu/data/mnp.svg",
      "name": "Северная Mariana Islands",
      "alpha2Code": "MP",
      "currencies": [
        {
          "code": "USD",
          "name": "Доллар США",
          "symbol": "$"
        }
      ],
      "englishName": "Северная Mariana Islands"
    },
    {
      "region": "Европа",
      "subregion": "Северная Европа",
      "flag": "https://restcountries.eu/data/nor.svg",
      "name": "Norway",
      "alpha2Code": "NO",
      "currencies": [
        {
          "code": "NOK",
          "name": "Norwegian krone",
          "symbol": "kr"
        }
      ],
      "englishName": "Norway"
    },
    {
      "region": "Азия",
      "subregion": "Западная Азия",
      "flag": "https://restcountries.eu/data/omn.svg",
      "name": "Oman",
      "alpha2Code": "OM",
      "currencies": [
        {
          "code": "OMR",
          "name": "Omani rial",
          "symbol": "ر.ع."
        }
      ],
      "englishName": "Oman"
    },
    {
      "region": "Азия",
      "subregion": "Южная Азия",
      "flag": "https://restcountries.eu/data/pak.svg",
      "name": "Pakistan",
      "alpha2Code": "PK",
      "currencies": [
        {
          "code": "PKR",
          "name": "Pakistani rupee",
          "symbol": "₨"
        }
      ],
      "englishName": "Pakistan"
    },
    {
      "region": "Океания",
      "subregion": "Micronesia",
      "flag": "https://restcountries.eu/data/plw.svg",
      "name": "Palau",
      "alpha2Code": "PW",
      "currencies": [
        {
          "code": "USD",
          "name": "Доллар США",
          "symbol": "$"
        }
      ],
      "englishName": "Palau"
    },
    {
      "region": "Азия",
      "subregion": "Западная Азия",
      "flag": "https://restcountries.eu/data/pse.svg",
      "name": "Palestine",
      "alpha2Code": "PS",
      "currencies": [
        {
          "code": "ILS",
          "name": "Israeli new sheqel",
          "symbol": "₪"
        }
      ],
      "englishName": "Palestine"
    },
    {
      "region": "Америка",
      "subregion": "Central America",
      "flag": "https://restcountries.eu/data/pan.svg",
      "name": "Panama",
      "alpha2Code": "PA",
      "currencies": [
        {
          "code": "PAB",
          "name": "Panamanian balboa",
          "symbol": "B/."
        },
        {
          "code": "USD",
          "name": "Доллар США",
          "symbol": "$"
        }
      ],
      "englishName": "Panama"
    },
    {
      "region": "Океания",
      "subregion": "Melanesia",
      "flag": "https://restcountries.eu/data/png.svg",
      "name": "Papua New Guinea",
      "alpha2Code": "PG",
      "currencies": [
        {
          "code": "PGK",
          "name": "Papua New Guinean kina",
          "symbol": "K"
        }
      ],
      "englishName": "Papua New Guinea"
    },
    {
      "region": "Америка",
      "subregion": "Южная America",
      "flag": "https://restcountries.eu/data/pry.svg",
      "name": "Paraguay",
      "alpha2Code": "PY",
      "currencies": [
        {
          "code": "PYG",
          "name": "Paraguayan guaraní",
          "symbol": "₲"
        }
      ],
      "englishName": "Paraguay"
    },
    {
      "region": "Америка",
      "subregion": "Южная America",
      "flag": "https://restcountries.eu/data/per.svg",
      "name": "Peru",
      "alpha2Code": "PE",
      "currencies": [
        {
          "code": "PEN",
          "name": "Peruvian sol",
          "symbol": "S/."
        }
      ],
      "englishName": "Peru"
    },
    {
      "region": "Азия",
      "subregion": "Южная-Восточная Азия",
      "flag": "https://restcountries.eu/data/phl.svg",
      "name": "Philippines",
      "alpha2Code": "PH",
      "currencies": [
        {
          "code": "PHP",
          "name": "Philippine peso",
          "symbol": "₱"
        }
      ],
      "englishName": "Philippines"
    },
    {
      "region": "Океания",
      "subregion": "Полинезия",
      "flag": "https://restcountries.eu/data/pcn.svg",
      "name": "Pitcairn",
      "alpha2Code": "PN",
      "currencies": [
        {
          "code": "NZD",
          "name": "New Zealand dollar",
          "symbol": "$"
        }
      ],
      "englishName": "Pitcairn"
    },
    {
      "region": "Европа",
      "subregion": "Восточная Европа",
      "flag": "https://restcountries.eu/data/pol.svg",
      "name": "Poland",
      "alpha2Code": "PL",
      "currencies": [
        {
          "code": "PLN",
          "name": "Polish złoty",
          "symbol": "zł"
        }
      ],
      "englishName": "Poland"
    },
    {
      "region": "Европа",
      "subregion": "Южная Европа",
      "flag": "https://restcountries.eu/data/prt.svg",
      "name": "Portugal",
      "alpha2Code": "PT",
      "currencies": [
        {
          "code": "EUR",
          "name": "Евро",
          "symbol": "€"
        }
      ],
      "englishName": "Portugal"
    },
    {
      "region": "Америка",
      "subregion": "Карибы",
      "flag": "https://restcountries.eu/data/pri.svg",
      "name": "Puerto Rico",
      "alpha2Code": "PR",
      "currencies": [
        {
          "code": "USD",
          "name": "Доллар США",
          "symbol": "$"
        }
      ],
      "englishName": "Puerto Rico"
    },
    {
      "region": "Азия",
      "subregion": "Западная Азия",
      "flag": "https://restcountries.eu/data/qat.svg",
      "name": "Qatar",
      "alpha2Code": "QA",
      "currencies": [
        {
          "code": "QAR",
          "name": "Qatari riyal",
          "symbol": "ر.ق"
        }
      ],
      "englishName": "Qatar"
    },
    {
      "region": "Европа",
      "subregion": "Восточная Европа",
      "flag": "https://restcountries.eu/data/kos.svg",
      "name": "Kosovo",
      "alpha2Code": "XK",
      "currencies": [
        {
          "code": "EUR",
          "name": "Евро",
          "symbol": "€"
        }
      ],
      "englishName": "Kosovo"
    },
    {
      "region": "Европа",
      "subregion": "Восточная Европа",
      "flag": "https://restcountries.eu/data/rou.svg",
      "name": "Romania",
      "alpha2Code": "RO",
      "currencies": [
        {
          "code": "RON",
          "name": "Romanian leu",
          "symbol": "lei"
        }
      ],
      "englishName": "Romania"
    },
    {
      "region": "Европа",
      "subregion": "Восточная Европа",
      "flag": "https://restcountries.eu/data/rus.svg",
      "name": "Russian Federation",
      "alpha2Code": "RU",
      "currencies": [
        {
          "code": "RUB",
          "name": "Russian ruble",
          "symbol": "₽"
        }
      ],
      "englishName": "Russian Federation"
    },
    {
      "region": "Африка",
      "subregion": "Восточная Африка",
      "flag": "https://restcountries.eu/data/rwa.svg",
      "name": "Rwanda",
      "alpha2Code": "RW",
      "currencies": [
        {
          "code": "RWF",
          "name": "Rwandan franc",
          "symbol": "Fr"
        }
      ],
      "englishName": "Rwanda"
    },
    {
      "region": "Америка",
      "subregion": "Карибы",
      "flag": "https://restcountries.eu/data/kna.svg",
      "name": "Saint Kitts and Nevis",
      "alpha2Code": "KN",
      "currencies": [
        {
          "code": "XCD",
          "name": "Восточнокарибский доллар",
          "symbol": "$"
        }
      ],
      "englishName": "Saint Kitts and Nevis"
    },
    {
      "region": "Америка",
      "subregion": "Карибы",
      "flag": "https://restcountries.eu/data/lca.svg",
      "name": "Saint Lucia",
      "alpha2Code": "LC",
      "currencies": [
        {
          "code": "XCD",
          "name": "Восточнокарибский доллар",
          "symbol": "$"
        }
      ],
      "englishName": "Saint Lucia"
    },
    {
      "region": "Америка",
      "subregion": "Карибы",
      "flag": "https://restcountries.eu/data/maf.svg",
      "name": "Saint Martin (French part)",
      "alpha2Code": "MF",
      "currencies": [
        {
          "code": "EUR",
          "name": "Евро",
          "symbol": "€"
        }
      ],
      "englishName": "Saint Martin (French part)"
    },
    {
      "region": "Америка",
      "subregion": "Северная America",
      "flag": "https://restcountries.eu/data/spm.svg",
      "name": "Saint Pierre and Miquelon",
      "alpha2Code": "PM",
      "currencies": [
        {
          "code": "EUR",
          "name": "Евро",
          "symbol": "€"
        }
      ],
      "englishName": "Saint Pierre and Miquelon"
    },
    {
      "region": "Америка",
      "subregion": "Карибы",
      "flag": "https://restcountries.eu/data/vct.svg",
      "name": "Saint Vincent and the Grenadines",
      "alpha2Code": "VC",
      "currencies": [
        {
          "code": "XCD",
          "name": "Восточнокарибский доллар",
          "symbol": "$"
        }
      ],
      "englishName": "Saint Vincent and the Grenadines"
    },
    {
      "region": "Океания",
      "subregion": "Полинезия",
      "flag": "https://restcountries.eu/data/wsm.svg",
      "name": "Samoa",
      "alpha2Code": "WS",
      "currencies": [
        {
          "code": "WST",
          "name": "Samoan tālā",
          "symbol": "T"
        }
      ],
      "englishName": "Samoa"
    },
    {
      "region": "Европа",
      "subregion": "Южная Европа",
      "flag": "https://restcountries.eu/data/smr.svg",
      "name": "San Marino",
      "alpha2Code": "SM",
      "currencies": [
        {
          "code": "EUR",
          "name": "Евро",
          "symbol": "€"
        }
      ],
      "englishName": "San Marino"
    },
    {
      "region": "Азия",
      "subregion": "Западная Азия",
      "flag": "https://restcountries.eu/data/sau.svg",
      "name": "Saudi Arabia",
      "alpha2Code": "SA",
      "currencies": [
        {
          "code": "SAR",
          "name": "Saudi riyal",
          "symbol": "ر.س"
        }
      ],
      "englishName": "Saudi Arabia"
    },
    {
      "region": "Африка",
      "subregion": "Западная Африка",
      "flag": "https://restcountries.eu/data/sen.svg",
      "name": "Senegal",
      "alpha2Code": "SN",
      "currencies": [
        {
          "code": "XOF",
          "name": "Западноафриканский франк КФА",
          "symbol": "Fr"
        }
      ],
      "englishName": "Senegal"
    },
    {
      "region": "Европа",
      "subregion": "Южная Европа",
      "flag": "https://restcountries.eu/data/srb.svg",
      "name": "Serbia",
      "alpha2Code": "RS",
      "currencies": [
        {
          "code": "RSD",
          "name": "Serbian dinar",
          "symbol": "дин."
        }
      ],
      "englishName": "Serbia"
    },
    {
      "region": "Африка",
      "subregion": "Восточная Африка",
      "flag": "https://restcountries.eu/data/syc.svg",
      "name": "Seychelles",
      "alpha2Code": "SC",
      "currencies": [
        {
          "code": "SCR",
          "name": "Seychellois rupee",
          "symbol": "₨"
        }
      ],
      "englishName": "Seychelles"
    },
    {
      "region": "Африка",
      "subregion": "Западная Африка",
      "flag": "https://restcountries.eu/data/sle.svg",
      "name": "Sierra Leone",
      "alpha2Code": "SL",
      "currencies": [
        {
          "code": "SLL",
          "name": "Sierra Leonean leone",
          "symbol": "Le"
        }
      ],
      "englishName": "Sierra Leone"
    },
    {
      "region": "Азия",
      "subregion": "Южная-Восточная Азия",
      "flag": "https://restcountries.eu/data/sgp.svg",
      "name": "Singapore",
      "alpha2Code": "SG",
      "currencies": [
        {
          "code": "BND",
          "name": "Brunei dollar",
          "symbol": "$"
        },
        {
          "code": "SGD",
          "name": "Singapore dollar",
          "symbol": "$"
        }
      ],
      "englishName": "Singapore"
    },
    {
      "region": "Америка",
      "subregion": "Карибы",
      "flag": "https://restcountries.eu/data/sxm.svg",
      "name": "Sint Maarten (Dutch part)",
      "alpha2Code": "SX",
      "currencies": [
        {
          "code": "ANG",
          "name": "Netherlands Antillean guilder",
          "symbol": "ƒ"
        }
      ],
      "englishName": "Sint Maarten (Dutch part)"
    },
    {
      "region": "Европа",
      "subregion": "Восточная Европа",
      "flag": "https://restcountries.eu/data/svk.svg",
      "name": "Slovakia",
      "alpha2Code": "SK",
      "currencies": [
        {
          "code": "EUR",
          "name": "Евро",
          "symbol": "€"
        }
      ],
      "englishName": "Slovakia"
    },
    {
      "region": "Европа",
      "subregion": "Южная Европа",
      "flag": "https://restcountries.eu/data/svn.svg",
      "name": "Slovenia",
      "alpha2Code": "SI",
      "currencies": [
        {
          "code": "EUR",
          "name": "Евро",
          "symbol": "€"
        }
      ],
      "englishName": "Slovenia"
    },
    {
      "region": "Океания",
      "subregion": "Melanesia",
      "flag": "https://restcountries.eu/data/slb.svg",
      "name": "Solomon Islands",
      "alpha2Code": "SB",
      "currencies": [
        {
          "code": "SBD",
          "name": "Solomon Islands dollar",
          "symbol": "$"
        }
      ],
      "englishName": "Solomon Islands"
    },
    {
      "region": "Африка",
      "subregion": "Восточная Африка",
      "flag": "https://restcountries.eu/data/som.svg",
      "name": "Somalia",
      "alpha2Code": "SO",
      "currencies": [
        {
          "code": "SOS",
          "name": "Somali shilling",
          "symbol": "Sh"
        }
      ],
      "englishName": "Somalia"
    },
    {
      "region": "Африка",
      "subregion": "Южная Африка",
      "flag": "https://restcountries.eu/data/zaf.svg",
      "name": "Южная Африка",
      "alpha2Code": "ZA",
      "currencies": [
        {
          "code": "ZAR",
          "name": "Южная Африкаn rand",
          "symbol": "R"
        }
      ],
      "englishName": "Южная Африка"
    },
    {
      "region": "Америка",
      "subregion": "Южная America",
      "flag": "https://restcountries.eu/data/sgs.svg",
      "name": "Южная Georgia and the Южная Sandwich Islands",
      "alpha2Code": "GS",
      "currencies": [
        {
          "code": "GBP",
          "name": "British pound",
          "symbol": "£"
        }
      ],
      "englishName": "Южная Georgia and the Южная Sandwich Islands"
    },
    {
      "region": "Азия",
      "subregion": "Восточная Азия",
      "flag": "https://restcountries.eu/data/kor.svg",
      "name": "Korea",
      "alpha2Code": "KR",
      "currencies": [
        {
          "code": "KRW",
          "name": "Южная Korean won",
          "symbol": "₩"
        }
      ],
      "englishName": "Korea"
    },
    {
      "region": "Африка",
      "subregion": "Средняя Африка",
      "flag": "https://restcountries.eu/data/ssd.svg",
      "name": "Южная Sudan",
      "alpha2Code": "SS",
      "currencies": [
        {
          "code": "SSP",
          "name": "Южная Sudanese pound",
          "symbol": "£"
        }
      ],
      "englishName": "Южная Sudan"
    },
    {
      "region": "Европа",
      "subregion": "Южная Европа",
      "flag": "https://restcountries.eu/data/esp.svg",
      "name": "Spain",
      "alpha2Code": "ES",
      "currencies": [
        {
          "code": "EUR",
          "name": "Евро",
          "symbol": "€"
        }
      ],
      "englishName": "Spain"
    },
    {
      "region": "Азия",
      "subregion": "Южная Азия",
      "flag": "https://restcountries.eu/data/lka.svg",
      "name": "Sri Lanka",
      "alpha2Code": "LK",
      "currencies": [
        {
          "code": "LKR",
          "name": "Sri Lankan rupee",
          "symbol": "Rs"
        }
      ],
      "englishName": "Sri Lanka"
    },
    {
      "region": "Африка",
      "subregion": "Северная Африка",
      "flag": "https://restcountries.eu/data/sdn.svg",
      "name": "Sudan",
      "alpha2Code": "SD",
      "currencies": [
        {
          "code": "SDG",
          "name": "Sudanese pound",
          "symbol": "ج.س."
        }
      ],
      "englishName": "Sudan"
    },
    {
      "region": "Америка",
      "subregion": "Южная America",
      "flag": "https://restcountries.eu/data/sur.svg",
      "name": "Suriname",
      "alpha2Code": "SR",
      "currencies": [
        {
          "code": "SRD",
          "name": "Surinamese dollar",
          "symbol": "$"
        }
      ],
      "englishName": "Suriname"
    },
    {
      "region": "Европа",
      "subregion": "Северная Европа",
      "flag": "https://restcountries.eu/data/sjm.svg",
      "name": "Svalbard and Jan Mayen",
      "alpha2Code": "SJ",
      "currencies": [
        {
          "code": "NOK",
          "name": "Norwegian krone",
          "symbol": "kr"
        }
      ],
      "englishName": "Svalbard and Jan Mayen"
    },
    {
      "region": "Африка",
      "subregion": "Южная Африка",
      "flag": "https://restcountries.eu/data/swz.svg",
      "name": "Swaziland",
      "alpha2Code": "SZ",
      "currencies": [
        {
          "code": "SZL",
          "name": "Swazi lilangeni",
          "symbol": "L"
        }
      ],
      "englishName": "Swaziland"
    },
    {
      "region": "Европа",
      "subregion": "Северная Европа",
      "flag": "https://restcountries.eu/data/swe.svg",
      "name": "Sweden",
      "alpha2Code": "SE",
      "currencies": [
        {
          "code": "SEK",
          "name": "Swedish krona",
          "symbol": "kr"
        }
      ],
      "englishName": "Sweden"
    },
    {
      "region": "Европа",
      "subregion": "Западная Европа",
      "flag": "https://restcountries.eu/data/che.svg",
      "name": "Switzerland",
      "alpha2Code": "CH",
      "currencies": [
        {
          "code": "CHF",
          "name": "Swiss franc",
          "symbol": "Fr"
        }
      ],
      "englishName": "Switzerland"
    },
    {
      "region": "Азия",
      "subregion": "Западная Азия",
      "flag": "https://restcountries.eu/data/syr.svg",
      "name": "Syrian Arab Republic",
      "alpha2Code": "SY",
      "currencies": [
        {
          "code": "SYP",
          "name": "Syrian pound",
          "symbol": "£"
        }
      ],
      "englishName": "Syrian Arab Republic"
    },
    {
      "region": "Азия",
      "subregion": "Восточная Азия",
      "flag": "https://restcountries.eu/data/twn.svg",
      "name": "Taiwan",
      "alpha2Code": "TW",
      "currencies": [
        {
          "code": "TWD",
          "name": "New Taiwan dollar",
          "symbol": "$"
        }
      ],
      "englishName": "Taiwan"
    },
    {
      "region": "Азия",
      "subregion": "Central Азия",
      "flag": "https://restcountries.eu/data/tjk.svg",
      "name": "Tajikistan",
      "alpha2Code": "TJ",
      "currencies": [
        {
          "code": "TJS",
          "name": "Tajikistani somoni",
          "symbol": "ЅМ"
        }
      ],
      "englishName": "Tajikistan"
    },
    {
      "region": "Африка",
      "subregion": "Восточная Африка",
      "flag": "https://restcountries.eu/data/tza.svg",
      "name": "Tanzania",
      "alpha2Code": "TZ",
      "currencies": [
        {
          "code": "TZS",
          "name": "Tanzanian shilling",
          "symbol": "Sh"
        }
      ],
      "englishName": "Tanzania"
    },
    {
      "region": "Азия",
      "subregion": "Южная-Восточная Азия",
      "flag": "https://restcountries.eu/data/tha.svg",
      "name": "Thailand",
      "alpha2Code": "TH",
      "currencies": [
        {
          "code": "THB",
          "name": "Thai baht",
          "symbol": "฿"
        }
      ],
      "englishName": "Thailand"
    },
    {
      "region": "Африка",
      "subregion": "Западная Африка",
      "flag": "https://restcountries.eu/data/tgo.svg",
      "name": "Togo",
      "alpha2Code": "TG",
      "currencies": [
        {
          "code": "XOF",
          "name": "Западноафриканский франк КФА",
          "symbol": "Fr"
        }
      ],
      "englishName": "Togo"
    },
    {
      "region": "Океания",
      "subregion": "Полинезия",
      "flag": "https://restcountries.eu/data/tkl.svg",
      "name": "Tokelau",
      "alpha2Code": "TK",
      "currencies": [
        {
          "code": "NZD",
          "name": "New Zealand dollar",
          "symbol": "$"
        }
      ],
      "englishName": "Tokelau"
    },
    {
      "region": "Океания",
      "subregion": "Полинезия",
      "flag": "https://restcountries.eu/data/ton.svg",
      "name": "Tonga",
      "alpha2Code": "TO",
      "currencies": [
        {
          "code": "TOP",
          "name": "Tongan paʻanga",
          "symbol": "T$"
        }
      ],
      "englishName": "Tonga"
    },
    {
      "region": "Америка",
      "subregion": "Карибы",
      "flag": "https://restcountries.eu/data/tto.svg",
      "name": "Trinidad and Tobago",
      "alpha2Code": "TT",
      "currencies": [
        {
          "code": "TTD",
          "name": "Trinidad and Tobago dollar",
          "symbol": "$"
        }
      ],
      "englishName": "Trinidad and Tobago"
    },
    {
      "region": "Африка",
      "subregion": "Северная Африка",
      "flag": "https://restcountries.eu/data/tun.svg",
      "name": "Tunisia",
      "alpha2Code": "TN",
      "currencies": [
        {
          "code": "TND",
          "name": "Tunisian dinar",
          "symbol": "د.ت"
        }
      ],
      "englishName": "Tunisia"
    },
    {
      "region": "Азия",
      "subregion": "Западная Азия",
      "flag": "https://restcountries.eu/data/tur.svg",
      "name": "Turkey",
      "alpha2Code": "TR",
      "currencies": [
        {
          "code": "TRY",
          "name": "Turkish lira",
          "symbol": null
        }
      ],
      "englishName": "Turkey"
    },
    {
      "region": "Азия",
      "subregion": "Central Азия",
      "flag": "https://restcountries.eu/data/tkm.svg",
      "name": "Turkmenistan",
      "alpha2Code": "TM",
      "currencies": [
        {
          "code": "TMT",
          "name": "Turkmenistan manat",
          "symbol": "m"
        }
      ],
      "englishName": "Turkmenistan"
    },
    {
      "region": "Америка",
      "subregion": "Карибы",
      "flag": "https://restcountries.eu/data/tca.svg",
      "name": "Turks and Caicos Islands",
      "alpha2Code": "TC",
      "currencies": [
        {
          "code": "USD",
          "name": "Доллар США",
          "symbol": "$"
        }
      ],
      "englishName": "Turks and Caicos Islands"
    },
    {
      "region": "Океания",
      "subregion": "Полинезия",
      "flag": "https://restcountries.eu/data/tuv.svg",
      "name": "Tuvalu",
      "alpha2Code": "TV",
      "currencies": [
        {
          "code": "AUD",
          "name": "Австралийский доллар",
          "symbol": "$"
        },
        {
          "code": "TVD[G]",
          "name": "Tuvaluan dollar",
          "symbol": "$"
        }
      ],
      "englishName": "Tuvalu"
    },
    {
      "region": "Африка",
      "subregion": "Восточная Африка",
      "flag": "https://restcountries.eu/data/uga.svg",
      "name": "Uganda",
      "alpha2Code": "UG",
      "currencies": [
        {
          "code": "UGX",
          "name": "Ugandan shilling",
          "symbol": "Sh"
        }
      ],
      "englishName": "Uganda"
    },
    {
      "region": "Европа",
      "subregion": "Восточная Европа",
      "flag": "https://restcountries.eu/data/ukr.svg",
      "name": "Ukraine",
      "alpha2Code": "UA",
      "currencies": [
        {
          "code": "UAH",
          "name": "Ukrainian hryvnia",
          "symbol": "₴"
        }
      ],
      "englishName": "Ukraine"
    },
    {
      "region": "Азия",
      "subregion": "Западная Азия",
      "flag": "https://restcountries.eu/data/are.svg",
      "name": "United Arab Emirates",
      "alpha2Code": "AE",
      "currencies": [
        {
          "code": "AED",
          "name": "United Arab Emirates dirham",
          "symbol": "د.إ"
        }
      ],
      "englishName": "United Arab Emirates"
    },
    {
      "region": "Европа",
      "subregion": "Северная Европа",
      "flag": "https://restcountries.eu/data/gbr.svg",
      "name": "United Kingdom of Great Britain and Северная Ireland",
      "alpha2Code": "GB",
      "currencies": [
        {
          "code": "GBP",
          "name": "British pound",
          "symbol": "£"
        }
      ],
      "englishName": "United Kingdom of Great Britain and Северная Ireland"
    },
    {
      "region": "Америка",
      "subregion": "Северная America",
      "flag": "https://restcountries.eu/data/usa.svg",
      "name": "United States of America",
      "alpha2Code": "US",
      "currencies": [
        {
          "code": "USD",
          "name": "Доллар США",
          "symbol": "$"
        }
      ],
      "englishName": "United States of America"
    },
    {
      "region": "Америка",
      "subregion": "Южная America",
      "flag": "https://restcountries.eu/data/ury.svg",
      "name": "Uruguay",
      "alpha2Code": "UY",
      "currencies": [
        {
          "code": "UYU",
          "name": "Uruguayan peso",
          "symbol": "$"
        }
      ],
      "englishName": "Uruguay"
    },
    {
      "region": "Азия",
      "subregion": "Central Азия",
      "flag": "https://restcountries.eu/data/uzb.svg",
      "name": "Uzbekistan",
      "alpha2Code": "UZ",
      "currencies": [
        {
          "code": "UZS",
          "name": "Uzbekistani so'm",
          "symbol": null
        }
      ],
      "englishName": "Uzbekistan"
    },
    {
      "region": "Океания",
      "subregion": "Melanesia",
      "flag": "https://restcountries.eu/data/vut.svg",
      "name": "Vanuatu",
      "alpha2Code": "VU",
      "currencies": [
        {
          "code": "VUV",
          "name": "Vanuatu vatu",
          "symbol": "Vt"
        }
      ],
      "englishName": "Vanuatu"
    },
    {
      "region": "Азия",
      "subregion": "Южная-Восточная Азия",
      "flag": "https://restcountries.eu/data/vnm.svg",
      "name": "Viet Nam",
      "alpha2Code": "VN",
      "currencies": [
        {
          "code": "VND",
          "name": "Vietnamese đồng",
          "symbol": "₫"
        }
      ],
      "englishName": "Viet Nam"
    },
    {
      "region": "Африка",
      "subregion": "Северная Африка",
      "flag": "https://restcountries.eu/data/esh.svg",
      "name": "Западная Sahara",
      "alpha2Code": "EH",
      "currencies": [
        {
          "code": "MAD",
          "name": "Moroccan dirham",
          "symbol": "د.م."
        },
        {
          "code": "DZD",
          "name": "Algerian dinar",
          "symbol": "د.ج"
        }
      ],
      "englishName": "Западная Sahara"
    },
    {
      "region": "Азия",
      "subregion": "Западная Азия",
      "flag": "https://restcountries.eu/data/yem.svg",
      "name": "Yemen",
      "alpha2Code": "YE",
      "currencies": [
        {
          "code": "YER",
          "name": "Yemeni rial",
          "symbol": "﷼"
        }
      ],
      "englishName": "Yemen"
    },
    {
      "region": "Африка",
      "subregion": "Восточная Африка",
      "flag": "https://restcountries.eu/data/zmb.svg",
      "name": "Zambia",
      "alpha2Code": "ZM",
      "currencies": [
        {
          "code": "ZMW",
          "name": "Zambian kwacha",
          "symbol": "ZK"
        }
      ],
      "englishName": "Zambia"
    },
    {
      "region": "Африка",
      "subregion": "Восточная Африка",
      "flag": "https://restcountries.eu/data/zwe.svg",
      "name": "Zimbabwe",
      "alpha2Code": "ZW",
      "currencies": [
        {
          "code": "BWP",
          "name": "Botswana pula",
          "symbol": "P"
        },
        {
          "code": "GBP",
          "name": "British pound",
          "symbol": "£"
        },
        {
          "code": "CNY",
          "name": "Chinese yuan",
          "symbol": "¥"
        },
        {
          "code": "EUR",
          "name": "Евро",
          "symbol": "€"
        },
        {
          "code": "INR",
          "name": "Indian rupee",
          "symbol": "₹"
        },
        {
          "code": "JPY",
          "name": "Japanese yen",
          "symbol": "¥"
        },
        {
          "code": "ZAR",
          "name": "Южная Африкаn rand",
          "symbol": "Rs"
        },
        {
          "code": "USD",
          "name": "Доллар США",
          "symbol": "$"
        }
      ],
      "englishName": "Zimbabwe"
    }
  ]
}